.gitignore
LICENSE
MANIFEST.in
README.md
setup.py
examples/HVAC.py
examples/QuadUtil.py
pyDR/__init__.py
pyDR/blopt.py
pyDR/dynamic_models.py
pyDR/simulation.py
pyDR/utils.py
pyDR.egg-info/PKG-INFO
pyDR.egg-info/SOURCES.txt
pyDR.egg-info/dependency_links.txt
pyDR.egg-info/requires.txt
pyDR.egg-info/top_level.txt
pyDR/data/CAISO_NBT.csv
pyDR/data/PDP_days.csv