Metadata-Version: 1.1
Name: pyDR
Version: 0.1.3
Summary: A package for simulating behavior of consumers facing dynamic electricity pricing.
Home-page: http://github.com/Balandat/pyDR
Author: Maximilian Balandat
Author-email: balandat@eecss.berkeley.edu
License: MIT
Keywords: economics,electricity,Demand Response
Platform: UNKNOWN
Classifier: Development Status :: 4 - Beta
Classifier: Topic :: Utilities
Classifier: License :: OSI Approved :: BSD License
